gustave/__init__.py
gustave/caching.py
gustave/patchers/__init__.py
gustave/patchers/core.py
gustave/patchers/keras.py
gustave/patchers/pandas.py
gustave/patchers/sklearn.py
gustave/utils.py
gustave-0.1.5.dist-info/WHEEL
gustave-0.1.5.dist-info/METADATA
gustave-0.1.5.dist-info/RECORD
