Metadata-Version: 2.1
Name: gustave
Version: 0.1.5
Summary: 
Author: Tomas Pereira de Vasconcelos
Author-email: tomasvasconcelos1@gmail.com
Requires-Python: >=3.7.1,<4.0.0
Classifier: Programming Language :: Python :: 3
Classifier: Programming Language :: Python :: 3.8
Classifier: Programming Language :: Python :: 3.9
Provides-Extra: pandas
Provides-Extra: sklearn
Provides-Extra: tensorflow
Requires-Dist: dill (>=0.3.1,<0.4.0)
Requires-Dist: pandas (>=1.0.0,<2.0.0); extra == "pandas"
Requires-Dist: scikit-learn; extra == "sklearn"
Requires-Dist: tensorflow (>=2.4.0,<3.0.0); extra == "tensorflow"
Requires-Dist: wrapt (>=1.12.1,<2.0.0)
